taxmyphage/__init__.py
taxmyphage/__main__.py
taxmyphage/actions.py
taxmyphage/classify.py
taxmyphage/cli.py
taxmyphage/download_check.py
taxmyphage/handle_files.py
taxmyphage/plot.py
taxmyphage/pmv.py
taxmyphage/utils.py
taxmyphage-0.3.6.dist-info/LICENSE
taxmyphage-0.3.6.dist-info/METADATA
taxmyphage-0.3.6.dist-info/WHEEL
taxmyphage-0.3.6.dist-info/entry_points.txt
taxmyphage-0.3.6.dist-info/RECORD
