Metadata-Version: 2.3
Name: taxmyphage
Version: 0.3.6
Summary: Script to assign taxonomy to a bacteriophage at the genus and species level
License: MIT
Keywords: Phage,Scientific/Engineering,Bio-Informatics,Taxonomy,Bacteriophage
Author: Andrew Millard
Author-email: adm39@leicester.ac.uk
Requires-Python: >=3.9,<3.13
Classifier: Development Status :: 5 - Production/Stable
Classifier: Environment :: Console
Classifier: Intended Audience :: Science/Research
Classifier: License :: OSI Approved :: MIT License
Classifier: Operating System :: POSIX
Classifier: Programming Language :: Python :: 3
Classifier: Programming Language :: Python :: 3.9
Classifier: Programming Language :: Python :: 3.10
Classifier: Programming Language :: Python :: 3.11
Classifier: Programming Language :: Python :: 3.12
Classifier: Topic :: Scientific/Engineering :: Bio-Informatics
Requires-Dist: biopython (>=1.81,<2.0)
Requires-Dist: icecream (>=2.1.3,<3.0.0)
Requires-Dist: matplotlib (>=3.8.0,<4.0.0)
Requires-Dist: networkx (>=3.1,<4.0)
Requires-Dist: numpy (>=1.26.0,<2.0.0)
Requires-Dist: openpyxl (>=3.1.2,<4.0.0)
Requires-Dist: pandas (>=2.1.1,<3.0.0)
Requires-Dist: scipy (>=1.11.3,<2.0.0)
Requires-Dist: seaborn (>=0.13,<0.14)
Requires-Dist: tqdm (>=4.66.1,<5.0.0)
Requires-Dist: wget (>=3.2,<4.0)
Requires-Dist: zipp (>=3.17.0,<4.0.0)
Project-URL: Bug Tracker, https://github.com/amillard/taxy_myPHAGE/issues
Project-URL: Homepage, https://github.com/amillard/tax_myPHAGE
Project-URL: Repository, https://github.com/amillard/tax_myPHAGE
